{
  "Item1": {
    "Name": "Hanzo Katarine",
    "ServerId": 99
  },
  "Item2": {
    "Leves": {
      "Allowances": 100,
      "LastUpdate": "2023-04-17T12:00:00Z"
    },
    "Squadron": {
      "MissionEnd": "0001-01-01T00:00:00",
      "TrainingEnd": "0001-01-01T00:00:00",
      "MissionId": 0,
      "TrainingId": 0,
      "NewRecruits": true
    },
    "Map": "2024-01-10T04:26:21.6532198Z",
    "MiniCactpot": {
      "LastUpdate": "2024-01-08T00:57:40.8318632Z",
      "Tickets": 3
    },
    "JumboCactpot": {
      "LastUpdate": "2024-01-08T00:58:52.9484032Z",
      "Tickets": [
        124,
        215,
        8008
      ]
    },
    "Delivery": {
      "Allowances": 12,
      "LastUpdate": "2024-01-09T08:00:03.4511473Z"
    },
    "Tribe": {
      "Allowances": 12,
      "LastUpdate": "2024-01-09T15:03:09.0292961Z"
    }
  }
}